dna_engine/__init__.py
dna_engine/actor.py
dna_engine/audio_manager.py
dna_engine/background.py
dna_engine/game.py
dna_engine/input_manager.py
dna_engine/text.py
dna_engine/world.py
dna_engine/tilemaps/__init__.py
dna_engine/tilemaps/tile.py
dna_engine/tilemaps/tile_map.py
dna_engine-1.0.7.dist-info/METADATA
dna_engine-1.0.7.dist-info/WHEEL
dna_engine-1.0.7.dist-info/top_level.txt
dna_engine-1.0.7.dist-info/RECORD
