Metadata-Version: 2.1
Name: dna-engine
Version: 1.0.7
Summary: PyGame Abstraction Library
Author: Liam Burns
Author-email: l.burns@dundeeandangus.ac.uk
Keywords: python,pygame,game development,beginner,education
Classifier: Development Status :: 3 - Alpha
Classifier: Intended Audience :: Education
Classifier: Programming Language :: Python :: 3
Classifier: Operating System :: MacOS :: MacOS X
Classifier: Operating System :: Microsoft :: Windows
Requires-Dist: pygame
Requires-Dist: pyinstaller
Requires-Dist: multipledispatch
